setup.py
Ella_Category_Subdomain.egg-info/PKG-INFO
Ella_Category_Subdomain.egg-info/SOURCES.txt
Ella_Category_Subdomain.egg-info/dependency_links.txt
Ella_Category_Subdomain.egg-info/requires.txt
Ella_Category_Subdomain.egg-info/top_level.txt
ella_category_subdomain/__init__.py
ella_category_subdomain/admin.py
ella_category_subdomain/conf.py
ella_category_subdomain/middleware.py
ella_category_subdomain/models.py
ella_category_subdomain/monkeypatch.py
ella_category_subdomain/newman_admin.py
ella_category_subdomain/util.py