Metadata-Version: 1.0
Name: Ella-Category-Subdomain
Version: 0.6.0
Summary: Use Ella categories as subdomains.
Home-page: http://github.com/sanomacz/ella-category-subdomain/
Author: Vitek Pliska
Author-email: whit@jizak.cz
License: BSD
Platform: UNKNOWN
Classifier: Development Status :: 4 - Beta
Classifier: Intended Audience :: Developers
Classifier: License :: OSI Approved :: BSD License
Classifier: Operating System :: OS Independent
Classifier: Framework :: Django
Classifier: Programming Language :: Python :: 2.5
Classifier: Programming Language :: Python :: 2.6
Classifier: Programming Language :: Python :: 2.7
Classifier: Operating System :: OS Independent
Classifier: Topic :: Internet :: WWW/HTTP :: Dynamic Content
Classifier: Topic :: Software Development :: Libraries :: Python Modules
